odoo9_addon_stock_deposit-9.0.1.0.1-py2.7-nspkg.pth
odoo9_addon_stock_deposit-9.0.1.0.1.dist-info/DESCRIPTION.rst
odoo9_addon_stock_deposit-9.0.1.0.1.dist-info/METADATA
odoo9_addon_stock_deposit-9.0.1.0.1.dist-info/RECORD
odoo9_addon_stock_deposit-9.0.1.0.1.dist-info/WHEEL
odoo9_addon_stock_deposit-9.0.1.0.1.dist-info/metadata.json
odoo9_addon_stock_deposit-9.0.1.0.1.dist-info/namespace_packages.txt
odoo9_addon_stock_deposit-9.0.1.0.1.dist-info/top_level.txt
odoo_addons/stock_deposit/README.rst
odoo_addons/stock_deposit/__init__.py
odoo_addons/stock_deposit/__openerp__.py
odoo_addons/stock_deposit/data/stock_deposit_data.xml
odoo_addons/stock_deposit/i18n/de.po
odoo_addons/stock_deposit/i18n/es.po
odoo_addons/stock_deposit/i18n/fr.po
odoo_addons/stock_deposit/i18n/it.po
odoo_addons/stock_deposit/i18n/pt_BR.po
odoo_addons/stock_deposit/i18n/sl.po
odoo_addons/stock_deposit/models/__init__.py
odoo_addons/stock_deposit/models/product.py
odoo_addons/stock_deposit/models/stock_location.py
odoo_addons/stock_deposit/models/stock_picking.py
odoo_addons/stock_deposit/models/stock_quant.py
odoo_addons/stock_deposit/models/stock_warehouse.py
odoo_addons/stock_deposit/static/description/icon.png
odoo_addons/stock_deposit/static/description/icon.svg
odoo_addons/stock_deposit/tests/__init__.py
odoo_addons/stock_deposit/tests/test_stock_deposit.py
odoo_addons/stock_deposit/views/product_view.xml
odoo_addons/stock_deposit/views/stock_dashboard.xml
odoo_addons/stock_deposit/views/stock_location_view.xml
odoo_addons/stock_deposit/views/stock_picking_view.xml
odoo_addons/stock_deposit/views/stock_quant_view.xml
odoo_addons/stock_deposit/views/stock_view.xml
odoo_addons/stock_deposit/wizards/__init__.py
odoo_addons/stock_deposit/wizards/stock_quant_wizard.py
odoo_addons/stock_deposit/wizards/stock_quant_wizard_view.xml
